fastapi_databasetk/__init__.py
fastapi_databasetk/objects/__init__.py
fastapi_databasetk/objects/base.py
fastapi_databasetk/objects/config.py
fastapi_databasetk/objects/database_async.py
fastapi_databasetk/objects/database_sync.py
fastapi_databasetk-1.0.1.dist-info/WHEEL
fastapi_databasetk-1.0.1.dist-info/METADATA
fastapi_databasetk-1.0.1.dist-info/RECORD
