Metadata-Version: 2.1
Name: fastapi-databasetk
Version: 1.0.1
Summary: 
License: MIT
Author: wayfaring-stranger
Author-email: zw6p226m@duck.com
Requires-Python: >=3.8,<4.0
Classifier: License :: OSI Approved :: MIT License
Classifier: Programming Language :: Python :: 3
Classifier: Programming Language :: Python :: 3.8
Classifier: Programming Language :: Python :: 3.9
Classifier: Programming Language :: Python :: 3.10
Classifier: Programming Language :: Python :: 3.11
Requires-Dist: databases (>=0.6.0,<0.7.0)
Requires-Dist: fastapi (>=0.89.1,<0.90.0)
Requires-Dist: pydantic (>=1.10.2,<2.0.0)
